uno/__init__.pyi
uno/py.typed
unohelper/__init__.pyi
unohelper/py.typed
types_uno_script-0.1.1.dist-info/LICENSE
types_uno_script-0.1.1.dist-info/METADATA
types_uno_script-0.1.1.dist-info/WHEEL
types_uno_script-0.1.1.dist-info/top_level.txt
types_uno_script-0.1.1.dist-info/RECORD
