Metadata-Version: 2.1
Name: types-uno-script
Version: 0.1.1
Summary: Type annotations for LibreOffice UNO Script
Home-page: https://github.com/Amourspirit/python-types-uno-script
Author: :Barry-Thomas-Paul: Moss
Author-email: bigbytetech@gmail.com
License: Apache Software License
Keywords: libreoffice,openoffice,typings,uno,ooouno,pyuno
Platform: UNKNOWN
Classifier: License :: OSI Approved :: Apache Software License
Classifier: Environment :: Other Environment
Classifier: Intended Audience :: Developers
Classifier: Operating System :: OS Independent
Classifier: Topic :: Office/Business
Classifier: Typing :: Typed
Classifier: Programming Language :: Python
Classifier: Programming Language :: Python :: 3
Classifier: Programming Language :: Python :: 3.7
Classifier: Programming Language :: Python :: 3.8
Classifier: Programming Language :: Python :: 3.9
Classifier: Programming Language :: Python :: 3.10
Requires-Python: >=3.7.0
License-File: LICENSE
Requires-Dist: typing-extensions (>=3.7.4.3) ; python_version < "3.7"
